jsoncomparekarate/__init__.py
jsoncomparekarate/jsoncomparekarate.py
jsoncomparekarate/jsoncomparekaratetest.py
json_compare_karate-1.0.dist-info/LICENSE
json_compare_karate-1.0.dist-info/METADATA
json_compare_karate-1.0.dist-info/WHEEL
json_compare_karate-1.0.dist-info/top_level.txt
json_compare_karate-1.0.dist-info/RECORD
