Metadata-Version: 2.1
Name: json-compare-karate
Version: 1.0
Summary: A recursive json comparison library that handles karate style json comparison
Home-page: https://github.com/vinitatgithub/jsoncomparekarate
Author: Vin Pat
Author-email: eatfrogfirst@outlook.com
License: UNKNOWN
Keywords: json comparison order karate optional fields
Platform: UNKNOWN
Classifier: Programming Language :: Python :: 3
Classifier: License :: OSI Approved :: MIT License
Classifier: Operating System :: OS Independent
Requires-Python: >=3.5
License-File: LICENSE
